{
  "main": {
    "id": "defed461d1cc5916",
    "type": "split",
    "children": [
      {
        "id": "385f57ac8e1cfec6",
        "type": "tabs",
        "children": [
          {
            "id": "ab8d7f1e960614e8",
            "type": "leaf",
            "state": {
              "type": "markdown",
              "state": {
                "file": "알고리즘 정리/1)정리.md",
                "mode": "source",
                "source": false
              }
            }
          },
          {
            "id": "f416cccf2f6be61e",
            "type": "leaf",
            "state": {
              "type": "markdown",
              "state": {
                "file": "알고리즘 정리/탐색/그리디(greedy).md",
                "mode": "source",
                "source": false
              }
            }
          }
        ],
        "currentTab": 1
      }
    ],
    "direction": "vertical"
  },
  "left": {
    "id": "eacda2dee9e7b73c",
    "type": "split",
    "children": [
      {
        "id": "cd54ae514b2264bd",
        "type": "tabs",
        "children": [
          {
            "id": "42de44e82678178f",
            "type": "leaf",
            "state": {
              "type": "search",
              "state": {
                "query": "",
                "matchingCase": false,
                "explainSearch": false,
                "collapseAll": false,
                "extraContext": false,
                "sortOrder": "alphabetical"
              }
            }
          },
          {
            "id": "408fbe75a45775cf",
            "type": "leaf",
            "state": {
              "type": "file-explorer",
              "state": {
                "sortOrder": "alphabetical"
              }
            }
          },
          {
            "id": "33c83ecfad6ae375",
            "type": "leaf",
            "state": {
              "type": "bookmarks",
              "state": {}
            }
          },
          {
            "id": "8570027aa05db322",
            "type": "leaf",
            "state": {
              "type": "mk-path-view",
              "state": {}
            }
          },
          {
            "id": "fbed8dd20da9861d",
            "type": "leaf",
            "state": {
              "type": "mk-path-view",
              "state": {}
            }
          }
        ],
        "currentTab": 1
      }
    ],
    "direction": "horizontal",
    "width": 275.5
  },
  "right": {
    "id": "9bef0bdb72496ace",
    "type": "split",
    "children": [
      {
        "id": "16824702c2c01dc3",
        "type": "tabs",
        "children": [
          {
            "id": "d1de61bc99429beb",
            "type": "leaf",
            "state": {
              "type": "backlink",
              "state": {
                "file": "알고리즘 정리/탐색/그리디(greedy).md",
                "collapseAll": false,
                "extraContext": false,
                "sortOrder": "alphabetical",
                "showSearch": false,
                "searchQuery": "",
                "backlinkCollapsed": false,
                "unlinkedCollapsed": true
              }
            }
          },
          {
            "id": "26254878742afed8",
            "type": "leaf",
            "state": {
              "type": "tag",
              "state": {
                "sortOrder": "frequency",
                "useHierarchy": true
              }
            }
          },
          {
            "id": "663ad35fc7f82641",
            "type": "leaf",
            "state": {
              "type": "outgoing-link",
              "state": {
                "file": "알고리즘 정리/탐색/그리디(greedy).md",
                "linksCollapsed": false,
                "unlinkedCollapsed": true
              }
            }
          },
          {
            "id": "804f6e808327c183",
            "type": "leaf",
            "state": {
              "type": "outline",
              "state": {
                "file": "알고리즘 정리/탐색/그리디(greedy).md"
              }
            }
          },
          {
            "id": "6c1c26a38678bae3",
            "type": "leaf",
            "state": {
              "type": "calendar",
              "state": {}
            }
          },
          {
            "id": "e67a60c749ee34eb",
            "type": "leaf",
            "state": {
              "type": "advanced-tables-toolbar",
              "state": {}
            }
          }
        ],
        "currentTab": 3
      }
    ],
    "direction": "horizontal",
    "width": 256
  },
  "left-ribbon": {
    "hiddenItems": {
      "switcher:퀵 스위처 열기": false,
      "graph:그래프 뷰 열기": false,
      "canvas:새 캔버스 만들기": false,
      "daily-notes:오늘의 데일리 노트 열기": false,
      "templates:템플릿 삽입": false,
      "command-palette:명령어 팔레트 열기": false,
      "obsidian-full-calendar:Open Full Calendar": false
    }
  },
  "active": "f416cccf2f6be61e",
  "lastOpenFiles": [
    "알고리즘 정리/탐색/탐색 정리.md",
    "알고리즘 정리/1)정리.md",
    "알고리즘 정리/재귀 함수/재귀 함수(Recursion).md",
    "알고리즘 정리/브루트포스(Brute Force)/브루트 포스(Brute Force).md",
    "알고리즘 정리/정렬/정렬 알고리즘 정리.md",
    "알고리즘 정리/정렬/합병정렬 , 병합정렬(Merge Sort).md",
    "알고리즘 정리/정렬/선택 정렬(Selection Sort).md",
    "알고리즘 정리/탐색/너비 탐색(BFS).md",
    "알고리즘 정리/탐색/깊이 탐색(DFS).md",
    "알고리즘 정리/백트래킹/백트래킹(Backtracking).md",
    "알고리즘 정리/에라토스테네스의 체/에라토스테네스의 체(Sieve of Eratosthenes).md",
    "알고리즘 정리/냅색 알고리즘(Knapsack)/냅색 알고리즘(Knapsack).md",
    "알고리즘 정리/다이나믹 프로그래밍(DP)/다이나믹 프로그래밍(Dynamic Programming)(동적 계획법).md",
    "Spaces/Home",
    "Spaces",
    "알고리즘 정리/탐색/선형 탐색.md",
    "알고리즘 정리/탐색/이진 탐색.md",
    "알고리즘 정리/최단거리 알고리즘/최단거리 알고리즘 정리.md",
    "알고리즘 정리/부분 배열 응용 알고리즘/부분 배열 응용 알고리즘 정리.md",
    "알고리즘 정리/선형구조/선형구조 정리.md",
    "알고리즘 정리/비선형구조/비선형구조 정리.md",
    "알고리즘 정리/비선형구조/그래프(Graph).md",
    "알고리즘 정리/비선형구조/트리(Tree).md",
    "알고리즘 정리/선형구조/스택(Stack).md",
    "알고리즘 정리/선형구조/큐(Queue).md",
    "알고리즘 정리/탐색/그리디(greedy).md",
    "알고리즘 정리/플로이드 워셜/플로이드 워셜.md",
    "알고리즘 정리/플로이드 워셜",
    "알고리즘 정리/부분 배열 응용 알고리즘/슬라이딩 윈도우 알고리즘(Sliding Window).md",
    "알고리즘 정리/백트래킹",
    "알고리즘 정리/에라토스테네스의 체",
    "알고리즘 정리/부분 배열 응용 알고리즘",
    "알고리즘 정리/최단거리 알고리즘",
    "알고리즘 정리/다이나믹 프로그래밍(DP)",
    "알고리즘 정리/냅색 알고리즘(Knapsack)",
    "알고리즘 정리/재귀 함수",
    "알고리즘 정리/이미지 폴더/DFS 이미지.gif",
    "알고리즘 정리/이미지 폴더/BFS 이미지.gif",
    "알고리즘 정리/이미지 폴더/그리디 알고리즘 이미지.png",
    "알고리즘 정리/이미지 폴더/이진 탐색 이미지.png",
    "알고리즘 정리/이미지 폴더/선형(순차) 탐색 이미지.gif",
    "알고리즘 정리/이미지 폴더/원형큐 이미지.jpg",
    "알고리즘 정리/이미지 폴더/인접리스트.png",
    "알고리즘 정리/이미지 폴더/인접행렬.png",
    "알고리즘 정리/이미지 폴더/가중치 그래프 이미지.png",
    "알고리즘 정리/이미지 폴더/방향 그래프.png"
  ]
}